vttmisc/__init__.py
vttmisc/__main__.py
vttmisc/tsi1.py
vttmisc/tsic.py
vttmisc-0.0.5.dist-info/LICENSE
vttmisc-0.0.5.dist-info/METADATA
vttmisc-0.0.5.dist-info/WHEEL
vttmisc-0.0.5.dist-info/top_level.txt
vttmisc-0.0.5.dist-info/RECORD
