Metadata-Version: 2.1
Name: vttmisc
Version: 0.0.5
Summary: A collection of misc scripts related to VTT
Home-page: https://github.com/aaronbell/vttmisc
Author: Aaron Bell
Author-email: hello@sajatypeworks.com
License: MIT
Platform: UNKNOWN
Classifier: Programming Language :: Python :: 3
Classifier: License :: OSI Approved :: MIT License
Classifier: Operating System :: OS Independent
Requires-Python: >=3.6
Requires-Dist: fontTools (>=4.15.0)
